latisse/__init__.py
latisse/cli.py
latisse/config.py
latisse/hooks.py
latisse/main.py
latisse-0.1.0.dist-info/METADATA
latisse-0.1.0.dist-info/WHEEL
latisse-0.1.0.dist-info/entry_points.txt
latisse-0.1.0.dist-info/RECORD
