Metadata-Version: 2.1
Name: latisse
Version: 0.1.0
Summary: A changelog generator
Author: walidsa3d
Requires-Python: >=3.10,<4.0
Classifier: Programming Language :: Python :: 3
Classifier: Programming Language :: Python :: 3.10
Classifier: Programming Language :: Python :: 3.11
Classifier: Programming Language :: Python :: 3.12
Classifier: Programming Language :: Python :: 3.13
Requires-Dist: click (>=8.1.3,<9.0.0)
Requires-Dist: gitpython (>=3.1.43,<4.0.0)
Requires-Dist: tomli (>=2.0.2,<3.0.0)
